 [
   {
   "latitude": "-1.3040869",
   "longitude": "36.81425",
   "name": "Bill",
   "who": "me",
   "description": "loywhefhbew bvbwbvwe",
   "gender": "male",      
   "time": "2022-04-21T18:25:43-05:00" 
},
{
   "latitude": "-1.3041860",
   "longitude": "36.81520",
   "name": "Pauline",
   "who": "me",
   "description": "loywhefhbew bvbwbvwe",
   "gender": "female",      
   "time": "2022-04-21T18:25:43-05:00" 
},
{
   "latitude": "-1.3042861",
   "longitude": "36.81621",
   "name": "Faith",
   "who": "me",
   "description": "loywhefhbew bvbwbvwe",
   "gender": "female",      
   "time": "2022-04-21T18:25:43-05:00" 
},
{
   "latitude": "-1.3043862",
   "longitude": "36.81722",
   "name": "Nathan",
   "who": "me",
   "description": "loywhefhbew bvbwbvwe",
   "gender": "male",      
   "time": "2022-04-21T18:25:43-05:00" 
},
{
   "latitude": "-1.3044863",
   "longitude": "36.81823",
   "name": "Mike",
   "who": "me",
   "description": "loywhefhbew bvbwbvwe",
   "gender": "male",      
   "time": "2022-04-21T18:25:43-05:00" 
},
{
   "latitude": "-1.3045864",
   "longitude": "36.81924",
   "name": "Mary",
   "who": "me",
   "description": "loywhefhbew bvbwbvwe",
   "gender": "female",      
   "time": "2022-04-21T18:25:43-05:00" 
},
{
   "latitude": "-1.3046865",
   "longitude": "36.81025",
   "name": "John",
   "who": "me",
   "description": "loywhefhbew bvbwbvwe",
   "gender": "male",      
   "time": "2022-04-21T18:25:43-05:00" 
},
{
   "latitude": "-1.3047866",
   "longitude": "36.81126",
   "name": "Joe",
   "who": "me",
   "description": "loywhefhbew bvbwbvwe",
   "gender": "male",      
   "time": "2022-04-21T18:25:43-05:00" 
},
{
   "latitude": "-1.3048867",
   "longitude": "36.81127",
   "name": "Joyce",
   "who": "me",
   "description": "loywhefhbew bvbwbvwe",
   "gender": "female",      
   "time": "2022-04-21T18:25:43-05:00" 
},
{
   "latitude": "-1.3049868",
   "longitude": "36.81228",
   "name": "Tanya",
   "who": "me",
   "description": "loywhefhbew bvbwbvwe",
   "gender": "female",      
   "time": "2022-04-21T18:25:43-05:00" 
},
{
   "latitude": "-1.3040869",
   "longitude": "36.81329",
   "name": "Carl",
   "who": "me",
   "description": "loywhefhbew bvbwbvwe",
   "gender": "male",      
   "time": "2022-04-21T18:25:43-05:00" 
}
]
 

